AUTHORS.rst
CHANGES.rst
MANIFEST.in
setup.py
humilis_es/__init__.py
humilis_es/meta.yaml.j2
humilis_es/outputs.yaml.j2
humilis_es/plugin.py
humilis_es/resources.yaml.j2
humilis_es.egg-info/PKG-INFO
humilis_es.egg-info/SOURCES.txt
humilis_es.egg-info/dependency_links.txt
humilis_es.egg-info/entry_points.txt
humilis_es.egg-info/not-zip-safe
humilis_es.egg-info/requires.txt
humilis_es.egg-info/top_level.txt