Metadata-Version: 1.1
Name: humilis-es
Version: 0.0.6
Summary: Humilis plug-in to create an Elasticsearch domain
Home-page: https://github.com/humilis/humilis-es
Author: German Gomez-Herrero, FindHotel BV
Author-email: german@findhotel.net
License: MIT
Platform: UNKNOWN
Classifier: Programming Language :: Python :: 3
